LICENSE
README.rst
manual_requirements.txt
requirements.txt
setup.py
periodical_requests_recorder/__init__.py
periodical_requests_recorder.egg-info/PKG-INFO
periodical_requests_recorder.egg-info/SOURCES.txt
periodical_requests_recorder.egg-info/dependency_links.txt
periodical_requests_recorder.egg-info/requires.txt
periodical_requests_recorder.egg-info/top_level.txt
scripts/periodical_recorder