Metadata-Version: 2.1
Name: periodical-requests-recorder
Version: 0.4.0
Home-page: https://github.com/fx-kirin/periodical_requests_recorder
Author: fx-kirin
Author-email: fx.kirin@gmail.com
License: MIT
Classifier: Development Status :: 2 - Pre-Alpha
Classifier: License :: OSI Approved :: MIT License
Classifier: Programming Language :: Python
Classifier: Programming Language :: Python :: 3
Classifier: Programming Language :: Python :: 3.4
Classifier: Programming Language :: Python :: 3.5
Classifier: Programming Language :: Python :: 3.6
Classifier: Programming Language :: Python :: 3.7
License-File: LICENSE
